evq/__init__.py
evq/algorithm.py
evq-0.0.2.dist-info/LICENSE
evq-0.0.2.dist-info/METADATA
evq-0.0.2.dist-info/WHEEL
evq-0.0.2.dist-info/top_level.txt
evq-0.0.2.dist-info/RECORD
